data_models/User.py
data_models/__init__.py
db_service/DbOptions.py
db_service/DbService.py
db_service/Query.py
db_service/__init__.py
myfinanceadvisorlib-0.0.4.dist-info/METADATA
myfinanceadvisorlib-0.0.4.dist-info/WHEEL
myfinanceadvisorlib-0.0.4.dist-info/top_level.txt
myfinanceadvisorlib-0.0.4.dist-info/RECORD
